ellc/__init__.py
ellc/fluxes.py
ellc/lc.py
ellc/ldy.py
ellc/libellc.so
ellc/rv.py
ellc/version.py
ellc-1.8.11.data/scripts/ellc_emcee
ellc-1.8.11.dist-info/licenses/LICENSE.txt
ellc-1.8.11.dist-info/METADATA
ellc-1.8.11.dist-info/WHEEL
ellc-1.8.11.dist-info/top_level.txt
ellc-1.8.11.dist-info/RECORD
